[
  {
    "id": 1,
    "biyearly_id": 1,
    "name": "Bulbasaur",
    "type": ["Plant", "Poison"],
    "photo": "./img/2010/1.svg",
    "instagram": "https://www.instagram.com/bulbasaur",
    "description": [
      "Bulbasaur is a dual-type Plant/Poison Pokémon introduced in Generation I.",
      "It evolves into Ivysaur starting at level 16, which evolves into Venusaur starting at level 32."
    ],
    "biyearly_gen": 1,
    "official_gen": 1,
    "year": 2010
  },
  {
    "id": 2,
    "biyearly_id": 2,
    "name": "Ivysaur",
    "type":  ["Plant", "Poison"],
    "photo": "./img/2010/2.svg",
    "instagram": "https://www.instagram.com/charmander",
    "description": [
      "to add;",
      "and, too."
    ],
    "biyearly_gen": 1,
    "official_gen": 1,
    "year": 2010
  },
  {
    "id": 3,
    "biyearly_id": 3,
    "name": "Venusaur",
    "type":  ["Plant", "Poison"],
    "photo": "./img/2010/3.svg",
    "instagram": "https://www.instagram.com/charmander",
    "description": [
      "to add;",
      "and, too."
    ],
    "biyearly_gen": 1,
    "official_gen": 1,
    "year": 2010
  },
  {
    "id": 4,
    "biyearly_id": 4,
    "name": "Charmander",
    "type": "Fire",
    "photo": "./img/2010/4.svg",
    "instagram": "https://www.instagram.com/charmander",
    "description": [
      "Charmander is a Fire-type Pokémon introduced in Generation I.",
      "It evolves into Charmeleon starting at level 16, which evolves into Charizard starting at level 36."
    ],
    "biyearly_gen": 1,
    "official_gen": 1,
    "year": 2010
  },
  {
    "id": 5,
    "biyearly_id": 5,
    "name": "Charmeleon",
    "type":  "Fire",
    "photo": "./img/2010/5.svg",
    "instagram": "https://www.instagram.com/charmander",
    "description": [
      "to add;",
      "and, too."
    ],
    "biyearly_gen": 1,
    "official_gen": 1,
    "year": 2010
  },
  {
    "id": 6,
    "biyearly_id": 6,
    "name": "Charizard",
    "type":  "Fire",
    "photo": "./img/2010/6.svg",
    "instagram": "https://www.instagram.com/charmander",
    "description": [
      "to add;",
      "and, too."
    ],
    "biyearly_gen": 1,
    "official_gen": 1,
    "year": 2010
  },
  {
    "id": 7,
    "biyearly_id": 7,
    "name": "Squirtle",
    "type": "Water",
    "photo": "./img/2011/7.svg",
    "instagram": "https://www.instagram.com/squirtle",
    "description": [
      "Squirtle is a Water-type Pokémon introduced in Generation I.",
      "It evolves into Wartortle starting at level 16, which evolves into Blastoise starting at level 36."
    ],
    "biyearly_gen": 1,
    "official_gen": 1,
    "year": 2011
  },
  {
    "id": 8,
    "biyearly_id": 8,
    "name": "Wartortle",
    "type":  "Water",
    "photo": "./img/2011/8.svg",
    "instagram": "https://www.instagram.com/charmander",
    "description": [
      "to add;",
      "and, too."
    ],
    "biyearly_gen": 1,
    "official_gen": 1,
    "year": 2011
  },
  {
    "id": 9,
    "biyearly_id": 9,
    "name": "Blastoise",
    "type":  "Water",
    "photo": "./img/2011/9.svg",
    "instagram": "https://www.instagram.com/charmander",
    "description": [
      "to add;",
      "and, too."
    ],
    "biyearly_gen": 1,
    "official_gen": 1,
    "year": 2011
  },
  {
    "id": 10,
    "biyearly_id": 10,
    "name": "Caterpie",
    "type": "Bug",
    "photo": "./img/2011/10.svg",
    "instagram": "https://www.instagram.com/p/what",
    "description": [
      "to add;",
      "and, too."
    ],
    "biyearly_gen": 1,
    "official_gen": 1,
    "year": 2011
  },
  {
    "id": 11,
    "biyearly_id": 11,
    "name": "Metapod",
    "type": "Bug",
    "photo": "./img/2011/11.svg",
    "instagram": "https://www.instagram.com/p/what",
    "description": [
      "to add;",
      "and, too."
    ],
    "biyearly_gen": 1,
    "official_gen": 1,
    "year": 2011
  },
  {
    "id": 12,
    "biyearly_id": 12,
    "name": "Butterfree",
    "type": ["Bug", "Flying"],
    "photo": "./img/2011/12.svg",
    "instagram": "https://www.instagram.com/p/what",
    "description": [
      "to add;",
      "and, too."
    ],
    "biyearly_gen": 1,
    "official_gen": 1,
    "year": 2011
  },
  {
    "id": 13,
    "biyearly_id": 13,
    "name": "Weedle",
    "type": ["Bug", "Poison"],
    "photo": "./img/2012/13.svg",
    "instagram": "https://www.instagram.com/p/what",
    "description": [
      "to add;",
      "and, too."
    ],
    "biyearly_gen": 2,
    "official_gen": 1,
    "year": 2012
  },
  {
    "id": 14,
    "biyearly_id": 14,
    "name": "Kakuna",
    "type": ["Bug", "Poison"],
    "photo": "./img/2012/14.svg",
    "instagram": "https://www.instagram.com/p/what",
    "description": [
      "to add;",
      "and, too."
    ],
    "biyearly_gen": 2,
    "official_gen": 1,
    "year": 2012
  },
  {
    "id": 15,
    "biyearly_id": 15,
    "name": "Beedrill",
    "type": ["Bug", "Poison"],
    "photo": "./img/2012/15.svg",
    "instagram": "https://www.instagram.com/p/what",
    "description": [
      "to add;",
      "and, too."
    ],
    "biyearly_gen": 2,
    "official_gen": 1,
    "year": 2012
  },
  {
    "id": 16,
    "biyearly_id": 16,
    "name": "Pidgey",
    "type": ["Animal", "Flying"],
    "photo": "./img/2013/16.svg",
    "instagram": "https://www.instagram.com/p/what",
    "description": [
      "to add;",
      "and, too."
    ],
    "biyearly_gen": 2,
    "official_gen": 1,
    "year": 2013
  },
  {
    "id": 17,
    "biyearly_id": 17,
    "name": "Pidgeotto",
    "type": ["Animal", "Flying"],
    "photo": "./img/2013/17.svg",
    "instagram": "https://www.instagram.com/p/what",
    "description": [
      "to add;",
      "and, too."
    ],
    "biyearly_gen": 2,
    "official_gen": 1,
    "year": 2013
  },
  {
    "id": 18,
    "biyearly_id": 18,
    "name": "Pidgeot",
    "type": ["Animal", "Flying"],
    "photo": "./img/2013/18.svg",
    "instagram": "https://www.instagram.com/p/what",
    "description": [
      "to add;",
      "and, too."
    ],
    "biyearly_gen": 2,
    "official_gen": 1,
    "year": 2013
  },
  {
    "id": 19,
    "biyearly_id": 19,
    "name": "Rattata",
    "type": "Animal",
    "photo": "./img/2013/19.svg",
    "instagram": "https://www.instagram.com/p/what",
    "description": [
      "to add;",
      "and, too."
    ],
    "biyearly_gen": 2,
    "official_gen": 1,
    "year": 2013
  },
  {
    "id": 20,
    "biyearly_id": 20,
    "name": "Raticate",
    "type": "Animal",
    "photo": "./img/2013/20.svg",
    "instagram": "https://www.instagram.com/p/what",
    "description": [
      "to add;",
      "and, too."
    ],
    "biyearly_gen": 2,
    "official_gen": 1,
    "year": 2013
  },
  {
    "id": 21,
    "biyearly_id": 21,
    "name": "Spearow",
    "type": ["Animal", "Flying"],
    "photo": "./img/2014/21.svg",
    "instagram": "https://www.instagram.com/p/what",
    "description": [
      "to add;",
      "and, too."
    ],
    "biyearly_gen": 3,
    "official_gen": 1,
    "year": 2014
  },
  {
    "id": 22,
    "biyearly_id": 22,
    "name": "Fearow",
    "type": ["Animal", "Flying"],
    "photo": "./img/2014/22.svg",
    "instagram": "https://www.instagram.com/p/what",
    "description": [
      "to add;",
      "and, too."
    ],
    "biyearly_gen": 3,
    "official_gen": 1,
    "year": 2014
  },
  {
    "id": 23,
    "biyearly_id": 23,
    "name": "Ekans",
    "type": "Poison",
    "photo": "./img/2014/23.svg",
    "instagram": "https://www.instagram.com/p/what",
    "description": [
      "to add;",
      "and, too."
    ],
    "biyearly_gen": 3,
    "official_gen": 1,
    "year": 2014
  },
  {
    "id": 24,
    "biyearly_id": 24,
    "name": "Arbok",
    "type": "Poison",
    "photo": "./img/2014/24.svg",
    "instagram": "https://www.instagram.com/p/what",
    "description": [
      "to add;",
      "and, too."
    ],
    "biyearly_gen": 3,
    "official_gen": 1,
    "year": 2014
  },

  {
    "id": 172,
    "biyearly_id": 25,
    "name": "Pichu",
    "type": "Electric",
    "photo": "./img/2015/172.svg",
    "instagram": "https://www.instagram.com/pikachu",
    "description": [
      "Pikachu is an Electric-type Pokémon introduced in Generation I.",
      "It evolves from Pichu when leveled up with high friendship and evolves into Raichu when exposed to a Thunder Stone."
    ],
    "biyearly_gen": 3,
    "official_gen": 2,
    "year": 2015
  },
  {
    "id": 25,
    "biyearly_id": 26,
    "name": "Pikachu",
    "type": "Electric",
    "photo": "./img/2015/25.svg",
    "instagram": "https://www.instagram.com/pikachu",
    "description": [
      "Pikachu is an Electric-type Pokémon introduced in Generation I.",
      "It evolves from Pichu when leveled up with high friendship and evolves into Raichu when exposed to a Thunder Stone."
    ],
    "biyearly_gen": 3,
    "official_gen": 1,
    "year": 2015
  },
  {
    "id": 26,
    "biyearly_id": 27,
    "name": "Raichu",
    "type": "Electric",
    "photo": "./img/2015/26.svg",
    "instagram": "https://www.instagram.com/pikachu",
    "description": [
      "Pikachu is an Electric-type Pokémon introduced in Generation I.",
      "It evolves from Pichu when leveled up with high friendship and evolves into Raichu when exposed to a Thunder Stone."
    ],
    "biyearly_gen": 3,
    "official_gen": 1,
    "year": 2015
  },
  {
    "id": 56,
    "biyearly_id": 28,
    "name": "Mankey",
    "type": "Fighting",
    "photo": "./img/2016/56.svg",
    "instagram": "https://www.instagram.com/p/what",
    "description": [
      "to add;",
      "and, too."
    ],
    "biyearly_gen": 4,
    "official_gen": 1,
    "year": 2016
  },
  {
    "id": 57,
    "biyearly_id": 29,
    "name": "Primeape",
    "type": "Fighting",
    "photo": "./img/2016/57.svg",
    "instagram": "https://www.instagram.com/p/what",
    "description": [
      "to add;",
      "and, too."
    ],
    "biyearly_gen": 4,
    "official_gen": 1,
    "year": 2016
  },
  {
    "id": 979,
    "biyearly_id": 29,
    "name": "Annihilape",
    "type": ["Fighting", "Ghost"],
    "photo": "./img/2016/979.svg",
    "instagram": "https://www.instagram.com/p/what",
    "description": [
      "to add;",
      "and, too."
    ],
    "biyearly_gen": 4,
    "official_gen": 9,
    "year": 2016
  },
  {
    "id": 74,
    "biyearly_id": 12,
    "name": "Geodude",
    "type": ["Rock", "Ground"],
    "photo": "./img/2016/74.svg",
    "instagram": "https://www.instagram.com/p/what",
    "description": [
      "to add;",
      "and, too."
    ],
    "biyearly_gen": 4,
    "official_gen": 1,
    "year": 2016
  },
  {
    "id": 92,
    "biyearly_id": 13,
    "name": "Gastly",
    "type": ["Ghost", "Poison"],
    "photo": "./img/2017/92.svg",
    "instagram": "https://www.instagram.com/p/what",
    "description": [
      "to add;",
      "and, too."
    ],
    "biyearly_gen": 4,
    "official_gen": 1,
    "year": 2017
  },
  {
    "id": 122,
    "biyearly_id": 14,
    "name": "Mr. Mime",
    "type": ["Psychic", "Fairy"],
    "photo": "./img/2017/122.svg",
    "instagram": "https://www.instagram.com/p/what",
    "description": [
      "to add;",
      "and, too."
    ],
    "biyearly_gen": 4,
    "official_gen": 1,
    "year": 2017
  },
  {
    "id": 137,
    "biyearly_id": 15,
    "name": "Porygon",
    "type": ["Neutral", "Paper"],
    "photo": "./img/2018/137.svg",
    "instagram": "https://www.instagram.com/p/what",
    "description": [
      "to add;",
      "and, too."
    ],
    "biyearly_gen": 5,
    "official_gen": 1,
    "year": 2018
  },
  {
    "id": 144,
    "biyearly_id": 16,
    "name": "Articuno",
    "type": ["Ice", "Flying"],
    "photo": "./img/2019/144.svg",
    "instagram": "https://www.instagram.com/p/what",
    "description": [
      "to add;",
      "and, too."
    ],
    "biyearly_gen": 5,
    "official_gen": 1,
    "year": 2019
  },
  {
    "id": 149,
    "biyearly_id": 17,
    "name": "Dragonite",
    "type": ["Dragon", "Flying"],
    "photo": "./img/2019/149.svg",
    "instagram": "https://www.instagram.com/p/what",
    "description": [
      "to add;",
      "and, too."
    ],
    "biyearly_gen": 5,
    "official_gen": 1,
    "year": 2019
  },
  {
    "id": 198,
    "biyearly_id": 18,
    "name": "Murkrow",
    "type": ["Dark", "Flying"],
    "photo": "./img/2020/198.svg",
    "instagram": "https://www.instagram.com/p/what",
    "description": [
      "to add;",
      "and, too."
    ],
    "biyearly_gen": 6,
    "official_gen": 2,
    "year": 2020
  },
  {
    "id": 208,
    "biyearly_id": 19,
    "name": "Steelix",
    "type": ["Steel", "Ground"],
    "photo": "./img/2020/208.svg",
    "instagram": "https://www.instagram.com/p/what",
    "description": [
      "to add;",
      "and, too."
    ],
    "biyearly_gen": 6,
    "official_gen": 2,
    "year": 2020
  },
  {
    "id": 233,
    "biyearly_id": 20,
    "name": "Porygon2",
    "type": ["Neutral", "Plastic"],
    "photo": "./img/2021/233.svg",
    "instagram": "https://www.instagram.com/p/what",
    "description": [
      "to add;",
      "and, too."
    ],
    "biyearly_gen": 6,
    "official_gen": 2,
    "year": 2021
  },
  {
    "id": 292,
    "biyearly_id": 21,
    "name": "Shedinja",
    "type": ["Bug", "Ghost", "Paper"],
    "photo": "./img/2022/292.svg",
    "instagram": "https://www.instagram.com/p/what",
    "description": [
      "to add;",
      "and, too."
    ],
    "biyearly_gen": 7,
    "official_gen": 3,
    "year": 2022
  },
  {
    "id": 474,
    "biyearly_id": 22,
    "name": "Porygon-Z",
    "type": ["Neutral", "Plastic"],
    "photo": "./img/2024/474.svg",
    "instagram": "https://www.instagram.com/p/what",
    "description": [
      "to add;",
      "and, too."
    ],
    "biyearly_gen": 8,
    "official_gen": 4,
    "year": 2024
  },
  {
    "id": 837,
    "biyearly_id": 23,
    "name": "Rolycoly",
    "type": ["Rock", "Rubber"],
    "photo": "./img/2022/837.svg",
    "instagram": "https://www.instagram.com/p/what",
    "description": [
      "to add;",
      "and, too."
    ],
    "biyearly_gen": 7,
    "official_gen": 8,
    "year": 2022
  },
  {
    "id": 868,
    "biyearly_id": 24,
    "name": "Milcery",
    "type": ["Fairy", "Sugar"],
    "photo": "./img/2023/868.svg",
    "instagram": "https://www.instagram.com/p/what",
    "description": [
      "to add;",
      "and, too."
    ],
    "biyearly_gen": 7,
    "official_gen": 8,
    "year": 2023
  },
  {
    "id": 932,
    "biyearly_id": 25,
    "name": "Nacli",
    "type": ["Rock", "Salt"],
    "photo": "./img/2023/932.svg",
    "instagram": "https://www.instagram.com/p/what",
    "description": [
      "to add;",
      "and, too."
    ],
    "biyearly_gen": 7,
    "official_gen": 9,
    "year": 2023
  },
  {
    "id": 2019,
    "biyearly_id": 1,
    "name": "Regitube",
    "type": ["Rubber", "Plastic"],
    "photo": "./img/2025/2019.svg",
    "instagram": "https://www.instagram.com/p/what",
    "description": [
      "to add;",
      "and, too."
    ],
    "biyearly_gen": 8,
    "official_gen": 0,
    "year": 2025
  },
  {
    "id": 2020,
    "biyearly_id": 2,
    "name": "Regikraft",
    "type": ["Paper"],
    "photo": "./img/2025/2020.svg",
    "instagram": "https://www.instagram.com/p/what",
    "description": [
      "to add;",
      "and, too."
    ],
    "biyearly_gen": 8,
    "official_gen": 0,
    "year": 2025
  }
]
